arrfunc/__init__.py
arrfunc/arrfunc.py
arrfunc/linalg.py
arrfunc/test.py
arrfunc/utils.py
arrfunc-1.0.dist-info/DESCRIPTION.rst
arrfunc-1.0.dist-info/METADATA
arrfunc-1.0.dist-info/RECORD
arrfunc-1.0.dist-info/WHEEL
arrfunc-1.0.dist-info/metadata.json
arrfunc-1.0.dist-info/top_level.txt
